{"enemy_memory": [{"id": 0, "last_seen": 1685979291.936764, "position": [129, 0, 116], "health": 100, "type": 1, "angle": -1}, {"id": 1, "last_seen": 1685979291.9139204, "position": [129, 0, 114], "health": 96, "type": 1, "angle": -1}, {"id": 2, "last_seen": 1685979287.3213727, "position": [120, 0, 129], "health": 98, "type": 1, "angle": -1}, {"id": 3, "last_seen": 1685979291.9743602, "position": [131, 0, 116], "health": 96, "type": 1, "angle": -1}, {"id": 4, "last_seen": 1685979292.0278573, "position": [134, 0, 119], "health": 78, "type": 1, "angle": -1}, {"id": 5, "last_seen": 1685979287.4885342, "position": [132, 0, 114], "health": 88, "type": 1, "angle": -1}, {"id": 6, "last_seen": 1685979287.378597, "position": [121, 0, 130], "health": 98, "type": 1, "angle": -1}, {"id": 7, "last_seen": 1685979287.5772994, "position": [133, 0, 115], "health": 78, "type": 1, "angle": -1}, {"id": 8, "last_seen": 1685979287.3624697, "position": [124, 0, 109], "health": 100, "type": 1, "angle": -1}, {"id": 9, "last_seen": 1685979292.0243373, "position": [133, 0, 120], "health": 100, "type": 1, "angle": -1}, {"id": 10, "last_seen": 1685979294.7981174, "position": [124, 0, 134], "health": 99, "type": 1, "angle": -1}, {"id": 11, "last_seen": 1685979287.6910026, "position": [134, 0, 116], "health": 70, "type": 1, "angle": -1}, {"id": 12, "last_seen": 1685979287.3750825, "position": [125, 0, 110], "health": 100, "type": 1, "angle": -1}, {"id": 13, "last_seen": 1685979287.3841047, "position": [124, 0, 111], "health": 100, "type": 1, "angle": -1}, {"id": 14, "last_seen": 1685979291.979871, "position": [138, 0, 120], "health": 7, "type": 1, "angle": -1}, {"id": 15, "last_seen": 1685979291.9262214, "position": [136, 0, 118], "health": 34, "type": 1, "angle": -1}, {"id": 16, "last_seen": 1685979291.9347649, "position": [128, 0, 137], "health": 91, "type": 1, "angle": -1}, {"id": 17, "last_seen": 1685979294.817782, "position": [138, 0, 123], "health": 74, "type": 1, "angle": -1}, {"id": 18, "last_seen": 1685979294.7638867, "position": [136, 0, 121], "health": 74, "type": 1, "angle": -1}, {"id": 19, "last_seen": 1685979291.9557235, "position": [130, 0, 115], "health": 96, "type": 1, "angle": -1}, {"id": 20, "last_seen": 1685979296.6153102, "position": [141, 0, 126], "health": 53, "type": 1, "angle": -1}, {"id": 21, "last_seen": 1685979294.81365, "position": [137, 0, 124], "health": 98, "type": 1, "angle": -1}, {"id": 22, "last_seen": 1685979292.0171838, "position": [129, 0, 138], "health": 89, "type": 1, "angle": -1}, {"id": 23, "last_seen": 1685979291.9723203, "position": [137, 0, 119], "health": 15, "type": 1, "angle": -1}, {"id": 24, "last_seen": 1685979296.367571, "position": [140, 0, 127], "health": 86, "type": 1, "angle": -1}, {"id": 25, "last_seen": 1685979291.9768686, "position": [130, 0, 117], "health": 100, "type": 1, "angle": -1}, {"id": 26, "last_seen": 1685979291.988809, "position": [132, 0, 117], "health": 96, "type": 1, "angle": -1}, {"id": 27, "last_seen": 1685979291.982442, "position": [131, 0, 118], "health": 100, "type": 1, "angle": -1}, {"id": 28, "last_seen": 1685979291.9872727, "position": [126, 0, 123], "health": 100, "type": 1, "angle": -1}, {"id": 29, "last_seen": 1685979292.0223377, "position": [130, 0, 139], "health": 87, "type": 1, "angle": -1}, {"id": 30, "last_seen": 1685979292.0358748, "position": [142, 0, 127], "health": 31, "type": 1, "angle": -1}, {"id": 31, "last_seen": 1685979294.7880156, "position": [132, 0, 141], "health": 75, "type": 1, "angle": -1}, {"id": 32, "last_seen": 1685979292.0717618, "position": [134, 0, 121], "health": 98, "type": 1, "angle": -1}, {"id": 33, "last_seen": 1685979294.75437, "position": [130, 0, 127], "health": 90, "type": 1, "angle": -1}, {"id": 34, "last_seen": 1685979292.0812857, "position": [135, 0, 120], "health": 74, "type": 1, "angle": -1}, {"id": 35, "last_seen": 1685979294.7374647, "position": [143, 0, 128], "health": 11, "type": 1, "angle": -1}, {"id": 36, "last_seen": 1685979294.803116, "position": [136, 0, 123], "health": 98, "type": 1, "angle": -1}, {"id": 37, "last_seen": 1685979294.7744374, "position": [144, 0, 129], "health": 3, "type": 1, "angle": -1}, {"id": 38, "last_seen": 1685979294.8056283, "position": [131, 0, 128], "health": 88, "type": 1, "angle": -1}, {"id": 39, "last_seen": 1685979294.812138, "position": [137, 0, 122], "health": 74, "type": 1, "angle": -1}, {"id": 40, "last_seen": 1685979295.5516772, "position": [138, 0, 144], "health": 65, "type": 1, "angle": -1}, {"id": 41, "last_seen": 1685979294.8106315, "position": [125, 0, 135], "health": 99, "type": 1, "angle": -1}, {"id": 42, "last_seen": 1685979294.8156462, "position": [132, 0, 129], "health": 88, "type": 1, "angle": -1}], "ally_memory": [{"id": 0, "last_seen": 1685979292.0136647, "position": [173, 0, 122], "health": 12, "type": 1, "angle": -1}, {"id": 1, "last_seen": 1685979294.867286, "position": [168, 0, 146], "health": 12, "type": 1, "angle": -1}, {"id": 2, "last_seen": 1685979290.6084752, "position": [162, 0, 143], "health": 8, "type": 4, "angle": -1}, {"id": 3, "last_seen": 1685979295.9810514, "position": [189.46966991411003, 0, 128.46966991411003], "health": 92, "type": 4, "angle": -1}, {"id": 4, "last_seen": 1685979287.453306, "position": [164.1968777079741, 0, 131.1968777079741], "health": 16, "type": 1, "angle": -1}, {"id": 5, "last_seen": 1685979295.9752924, "position": [185.0908116907961, 0, 155.0908116907961], "health": 100, "type": 2, "angle": -1}, {"id": 6, "last_seen": 1685979292.1277142, "position": [177, 0, 145.90000000000026], "health": 9, "type": 2, "angle": -1}, {"id": 7, "last_seen": 1685979295.118966, "position": [195.68180194846602, 0, 140.68180194846602], "health": 98, "type": 4, "angle": -1}, {"id": 8, "last_seen": 1685979295.1231968, "position": [191, 0, 154], "health": 94, "type": 1, "angle": -1}], "pack_memory": [{"id": 0, "last_seen": 1685979286.6853552, "position": [172.28988179249177, 0, 140.35858863329017], "type": 1001}, {"id": 0, "last_seen": 1685979287.4593122, "position": [175.4724730338931, 0, 138.2691791398448], "type": 1001}, {"id": 0, "last_seen": 1685979287.4608204, "position": [176.21574469473418, 0, 137.86912950459177], "type": 1001}, {"id": 0, "last_seen": 1685979267.863993, "position": [172.14596666445868, 0, 139.3298482360797], "type": 1001}, {"id": 0, "last_seen": 1685979287.4314964, "position": [181.86180845890223, 0.0, 144.61588231463892], "type": 1001}, {"id": 0, "last_seen": 1685979290.5002902, "position": [182.5261160618908, 0.0, 142.7762963370918], "type": 1001}, {"id": 0, "last_seen": 1685979287.4400063, "position": [178.45847856110333, 0.0, 144.74334446273252], "type": 1001}, {"id": 0, "last_seen": 1685979287.2210515, "position": [181.08875984069397, 0.0, 146.63127747493212], "type": 1001}, {"id": 0, "last_seen": 1685979295.17662, "position": [191.19386034987312, 0, 147.53072480369576], "type": 1001}, {"id": 0, "last_seen": 1685979287.4251525, "position": [171.31839775005975, 0, 151.15869007741736], "type": 1002}, {"id": 0, "last_seen": 1685979287.195481, "position": [171.06410656381686, 0, 151.67245932575764], "type": 1002}, {"id": 0, "last_seen": 1685979287.2004893, "position": [173.07446945087568, 0, 152.6851044137739], "type": 1002}, {"id": 0, "last_seen": 1685979287.2054877, "position": [172.93392695343738, 0, 151.5976141412545], "type": 1002}, {"id": 0, "last_seen": 1685979295.1685925, "position": [193.8117706193054, 0.0, 132.5893295112461], "type": 1002}, {"id": 0, "last_seen": 1685979295.1705925, "position": [195.22762578590027, 0.0, 132.90732306909885], "type": 1002}, {"id": 0, "last_seen": 1685979295.1725926, "position": [197.64406627602568, 0.0, 132.96686900472614], "type": 1002}, {"id": 0, "last_seen": 1685979295.1731071, "position": [194.23720802820353, 0.0, 132.07933600805052], "type": 1002}, {"id": 0, "last_seen": 1685979295.139041, "position": [199.5327289892279, 0.0, 148.48940522172617], "type": 1002}, {"id": 0, "last_seen": 1685979295.1474159, "position": [203.03484035176263, 0.0, 148.66382410842587], "type": 1002}, {"id": 0, "last_seen": 1685979295.1604974, "position": [200.11460614938858, 0.0, 146.38791099790305], "type": 1002}, {"id": 0, "last_seen": 1685979295.164526, "position": [201.5734088047392, 0.0, 144.66735426633016], "type": 1002}, {"id": 0, "last_seen": 1685979295.1751018, "position": [202.62563120894262, 0.0, 146.31684971877002], "type": 1002}, {"id": 0, "last_seen": 1685979292.125702, "position": [166.00898336013842, 0.0, 147.07062450568145], "type": 1002}, {"id": 0, "last_seen": 1685979295.1776438, "position": [196.20097150800737, 0.0, 131.68581750125364], "type": 1002}], "time": 1685979297.8339486, "pos": [183, 0.0, 143], "dest": [182.5261160618908, 0.0, 142.7762963370918], "health": 7, "ammo": 100, "safest_point": [-1, -1, -1]}